pymediatracker/__init__.py
pymediatracker/client.py
pymediatracker/const.py
pymediatracker/exceptions.py
pymediatracker/objects/__init__.py
pymediatracker/objects/base.py
pymediatracker/objects/calendar.py
pymediatracker/objects/config.py
pymediatracker/objects/item.py
pymediatracker-0.1.3.dist-info/METADATA
pymediatracker-0.1.3.dist-info/WHEEL
pymediatracker-0.1.3.dist-info/RECORD
