Metadata-Version: 2.1
Name: pymediatracker
Version: 0.1.3
Summary: Asynchronous python client for MediaTracker.
Home-page: https://github.com/jonkristian/pymediatracker
License: MIT
Keywords: mediatracker,api,async,client
Author: Jon Kristian Nilsen
Author-email: hello@jonkristian.no
Requires-Python: >=3.8,<4.0
Classifier: License :: OSI Approved :: MIT License
Classifier: Programming Language :: Python :: 3
Classifier: Programming Language :: Python :: 3.8
Classifier: Programming Language :: Python :: 3.9
Classifier: Programming Language :: Python :: 3.10
Classifier: Programming Language :: Python :: 3.11
Classifier: Programming Language :: Python :: 3.12
Requires-Dist: aiohttp (>=3.7.4,<4.0.0)
Project-URL: Documentation, https://github.com/jonkristian/pymediatracker
Project-URL: Repository, https://github.com/jonkristian/pymediatracker
